argorator/__init__.py
argorator/analyzers.py
argorator/annotations.py
argorator/cli.py
argorator/compilation.py
argorator/context.py
argorator/contexts.py
argorator/execution.py
argorator/models.py
argorator/pipeline.py
argorator/registry.py
argorator/testing.py
argorator/transformers.py
argorator/validators.py
argorator/macros/__init__.py
argorator/macros/models.py
argorator/macros/parser.py
argorator/macros/processor.py
argorator-0.6.0.dist-info/licenses/LICENSE
argorator-0.6.0.dist-info/METADATA
argorator-0.6.0.dist-info/WHEEL
argorator-0.6.0.dist-info/entry_points.txt
argorator-0.6.0.dist-info/top_level.txt
argorator-0.6.0.dist-info/RECORD
