Metadata-Version: 2.4
Name: argorator
Version: 0.6.0
Summary: CLI to wrap shell scripts and expose variables/positionals as argparse options
Author: Argorator
Keywords: cli,shell,argparse,bash,scripting
Classifier: Programming Language :: Python :: 3
Classifier: License :: OSI Approved :: MIT License
Classifier: Operating System :: OS Independent
Requires-Python: >=3.9
License-File: LICENSE
Requires-Dist: pydantic>=2.0
Requires-Dist: parsy>=2.1
Dynamic: license-file
